{
  "parcel_id": "pcl_3236c625b8c5",
  "ref_id": "REF-001",
  "route": [
    {
      "event": "processing_started",
      "timestamp": 1769847595,
      "agent": "docling.processor.py",
      "context": {
        "batch_id": "batch_20260131_045514"
      }
    },
    {
      "event": "processing_completed",
      "timestamp": 1769847603,
      "agent": "docling.processor.py",
      "context": {
        "strategy": "standard",
        "page_count": 14,
        "chunk_count": 21
      }
    }
  ]
}
